setup.py
pyorbited/LICENSE.txt
pyorbited/__init__.py
pyorbited/event.py
pyorbited/io.py
pyorbited/simple.py
pyorbited/twistedorbit.py
pyorbited.egg-info/PKG-INFO
pyorbited.egg-info/SOURCES.txt
pyorbited.egg-info/dependency_links.txt
pyorbited.egg-info/not-zip-safe
pyorbited.egg-info/requires.txt
pyorbited.egg-info/top_level.txt
