Metadata-Version: 1.0
Name: pyorbited
Version: 0.2.0
Summary: A python client for Orbited (Orbit Event Daemon), a COMET server. Includes three implementations: pyevent, twisted, basic sockets.
Home-page: http://www.orbited.org
Author: Michael Carter
Author-email: CarterMichael@gmail.com
License: MIT License
Download-URL: http://www.orbited.org/download.html
Platform: UNKNOWN
Classifier: Development Status :: 3 - Alpha
Classifier: Environment :: Console
Classifier: Intended Audience :: Developers
Classifier: License :: OSI Approved :: MIT License
Classifier: Operating System :: OS Independent
Classifier: Programming Language :: Python
Classifier: Topic :: Software Development :: Libraries :: Python Modules
